serialdatalog/__init__.py
serialdatalog/datalog.py
serialdatalog-0.1.7.dist-info/METADATA
serialdatalog-0.1.7.dist-info/WHEEL
serialdatalog-0.1.7.dist-info/RECORD
