Metadata-Version: 2.1
Name: serialdatalog
Version: 0.1.7
Summary: Logs data coming from a serial port
Author: Alex
Author-email: adrysdale@protonmail.com
Requires-Python: >=3.10,<4.0
Classifier: Programming Language :: Python :: 3
Classifier: Programming Language :: Python :: 3.10
Classifier: Programming Language :: Python :: 3.11
Requires-Dist: pyserial (>=3.5,<4.0)
